djangoautoconf/__init__.py
djangoautoconf/auto_conf_signals.py
djangoautoconf/auto_conf_urls.py
djangoautoconf/auto_conf_utils.py
djangoautoconf/base_setting_storage.py
djangoautoconf/base_settings.py
djangoautoconf/django_adv_zip_template_loader.py
djangoautoconf/django_autoconf.py
djangoautoconf/django_dev_server_auto_conf.py
djangoautoconf/django_setting_manager.py
djangoautoconf/django_utils.py
djangoautoconf/django_zip_template_loader.py
djangoautoconf/djangoautoconf_settings.py
djangoautoconf/local_key_manager.py
djangoautoconf/object_copier.py
djangoautoconf/req_with_auth.py
djangoautoconf/sqlite_database.py
djangoautoconf/urls.py
djangoautoconf/ajax_select_utils/__init__.py
djangoautoconf/ajax_select_utils/ajax_select_channel_generator.py
djangoautoconf/ajax_select_utils/channel_creator_for_model.py
djangoautoconf/auth/__init__.py
djangoautoconf/auth/ldap_backend_wrapper.py
djangoautoconf/auth/login.py
djangoautoconf/auth/login_exceptions.py
djangoautoconf/auth/req_auth.py
djangoautoconf/auth/req_auth_base_backend.py
djangoautoconf/auth/req_auth_super_password_backend.py
djangoautoconf/auth/session_backend.py
djangoautoconf/auth/username_password_backend.py
djangoautoconf/auto_conf_admin_tools/__init__.py
djangoautoconf/auto_conf_admin_tools/action_feature.py
djangoautoconf/auto_conf_admin_tools/additional_attr.py
djangoautoconf/auto_conf_admin_tools/admin_attr_feature.py
djangoautoconf/auto_conf_admin_tools/admin_feature_base.py
djangoautoconf/auto_conf_admin_tools/admin_register.py
djangoautoconf/auto_conf_admin_tools/filter_horizontal_feature.py
djangoautoconf/auto_conf_admin_tools/filter_item_feature.py
djangoautoconf/auto_conf_admin_tools/foreign_key_auto_complete.py
djangoautoconf/auto_conf_admin_tools/guardian_feature.py
djangoautoconf/auto_conf_admin_tools/import_export_feature.py
djangoautoconf/auto_conf_admin_tools/list_and_search.py
djangoautoconf/auto_conf_admin_tools/model_with_full_permission_feature.py
djangoautoconf-2.0.11.dist-info/AUTHORS.rst
djangoautoconf-2.0.11.dist-info/LICENSE
djangoautoconf-2.0.11.dist-info/METADATA
djangoautoconf-2.0.11.dist-info/WHEEL
djangoautoconf-2.0.11.dist-info/top_level.txt
djangoautoconf-2.0.11.dist-info/RECORD
