Metadata-Version: 2.1
Name: djangoautoconf
Version: 2.0.11
Summary: Create a package to ease setting django project settings.
Home-page: https://github.com/weijia/djangoautoconf
Author: Richard Wang
Author-email: richardwangwang@gmail.com
License: BSD
Keywords: djangoautoconf
Platform: UNKNOWN
Classifier: Development Status :: 2 - Pre-Alpha
Classifier: Intended Audience :: Developers
Classifier: License :: OSI Approved :: BSD License
Classifier: Natural Language :: English
Classifier: Programming Language :: Python :: 2
Classifier: Programming Language :: Python :: 2.6
Classifier: Programming Language :: Python :: 2.7
Classifier: Programming Language :: Python :: 3
Classifier: Programming Language :: Python :: 3.3
Requires-Dist: django-extensions
Requires-Dist: ufs-tools
Requires-Dist: django-tastypie
Requires-Dist: django-jquery-ui
Requires-Dist: django-import-export
Requires-Dist: djangorestframework
Requires-Dist: easy-thumbnails
Requires-Dist: python-social-auth (<=0.2.21)
Requires-Dist: django-settings
Requires-Dist: django-simplemenu-simplified
Requires-Dist: django-filter (<2)
Requires-Dist: django-ajax-selects
